cacahuate/__init__.py
cacahuate/cascade.py
cacahuate/errors.py
cacahuate/forms.py
cacahuate/grammar.py
cacahuate/handler.py
cacahuate/imports.py
cacahuate/indexes.py
cacahuate/inputs.py
cacahuate/jsontypes.py
cacahuate/main.py
cacahuate/models.py
cacahuate/mongo.py
cacahuate/node.py
cacahuate/settings.py
cacahuate/tasks.py
cacahuate/templates.py
cacahuate/version.txt
cacahuate/xml.py
cacahuate/auth/base.py
cacahuate/auth/backends/anyone.py
cacahuate/auth/backends/impersonate.py
cacahuate/auth/backends/ldap.py
cacahuate/auth/hierarchy/anyone.py
cacahuate/auth/hierarchy/backref.py
cacahuate/grammars/condition.g
cacahuate/http/__init__.py
cacahuate/http/converters.py
cacahuate/http/error_handlers.py
cacahuate/http/errors.py
cacahuate/http/middleware.py
cacahuate/http/mongo.py
cacahuate/http/validation.py
cacahuate/http/wsgi.py
cacahuate/http/views/api.py
cacahuate/http/views/auth.py
cacahuate/http/views/templates.py
cacahuate/templates/summary.html
cacahuate/xml/process-spec.rng
cacahuate-3.14.1.dist-info/LICENSE.txt
cacahuate-3.14.1.dist-info/METADATA
cacahuate-3.14.1.dist-info/WHEEL
cacahuate-3.14.1.dist-info/entry_points.txt
cacahuate-3.14.1.dist-info/top_level.txt
cacahuate-3.14.1.dist-info/RECORD
