Metadata-Version: 2.1
Name: cacahuate
Version: 3.14.1
Summary: The process virtual machine
Home-page: https://github.com/tracsa/cacahuate
Author: Abraham Toriz Cruz
Author-email: categulario@gmail.com
License: MIT
Keywords: process
Platform: UNKNOWN
Classifier: Development Status :: 4 - Beta
Classifier: Intended Audience :: Developers
Classifier: Topic :: Software Development :: Libraries :: Python Modules
Classifier: License :: OSI Approved :: MIT License
Classifier: Programming Language :: Python :: 3
Classifier: Programming Language :: Python :: 3.6
License-File: LICENSE.txt
Requires-Dist: Flask-Coralillo
Requires-Dist: Flask-Cors
Requires-Dist: Flask-PyMongo (<2.0)
Requires-Dist: flask-sse
Requires-Dist: case-conversion
Requires-Dist: coralillo (>=2.1)
Requires-Dist: redis (>=3)
Requires-Dist: flask (<2.0,>=1.0)
Requires-Dist: itacate
Requires-Dist: lark-parser (>=0.6)
Requires-Dist: ldap3
Requires-Dist: pika (>=1.0)
Requires-Dist: simplejson
Requires-Dist: requests
Requires-Dist: passlib
Requires-Dist: jsonpath-rw
Requires-Dist: jinja2
Requires-Dist: werkzeug (<1.0)
Requires-Dist: celery
